backstage/.private
backstage/__init__.py
backstage/__main__.py
backstage/cmdline.py
backstage/constant.py
backstage/default_tasks
backstage/oneline.py
backstage/cli/__init__.py
backstage/cli/build.py
backstage/cli/init.py
backstage/cli/release.py
backstage/cli/run.py
backstage/cli/setup.py
backstage/cli/version.py
backstage/constant/.private
backstage/constant/__init__.py
backstage/core/.private
backstage/core/__init__.py
backstage/core/backstage_setup.py
backstage/core/building.py
backstage/core/constant.py
backstage/core/dist.py
backstage/core/funcs.py
backstage/core/github_client.py
backstage/core/hooking.py
backstage/core/initialization.py
backstage/core/installation.py
backstage/core/lite_test_runner.py
backstage/core/publishing.py
backstage/core/pymisc.py
backstage/core/releaser.py
backstage/core/runner.py
backstage/core/tasks.py
backstage/core/versioning.py
backstage/default_json/PyrusticData/manager_shared_data_default.json
backstage/default_json/pyrustic_data/build_report_default.json
backstage/default_json/pyrustic_data/hooking_default.json
backstage/default_json/pyrustic_data/hubstore_default.json
backstage/default_json/pyrustic_data/release_info_default.json
backstage/error/__init__.py
backstage/handler/.private
backstage/handler/__init__.py
backstage/handler/add_handler.py
backstage/handler/build_handler.py
backstage/handler/hub_handler.py
backstage/handler/init_handler.py
backstage/handler/link_handler.py
backstage/handler/private
backstage/handler/recent_handler.py
backstage/handler/release_handler.py
backstage/handler/relink_handler.py
backstage/handler/run_handler.py
backstage/handler/target_handler.py
backstage/handler/unlink_handler.py
backstage/handler/version_handler.py
backstage/namespace/.private
backstage/namespace/__init__.py
backstage/pattern/.private
backstage/pattern/__init__.py
backstage/pyrustic_data/backstage/config/build.json
backstage/pyrustic_data/backstage/config/init.json
backstage/pyrustic_data/backstage/config/release.json
backstage-0.0.22.dist-info/LICENSE
backstage-0.0.22.dist-info/METADATA
backstage-0.0.22.dist-info/WHEEL
backstage-0.0.22.dist-info/entry_points.txt
backstage-0.0.22.dist-info/top_level.txt
backstage-0.0.22.dist-info/RECORD
