Metadata-Version: 2.1
Name: backstage
Version: 0.0.22
Summary: Three-speed scripting language and task automation tool
Home-page: https://github.com/pyrustic/backstage
Author: Pyrustic Evangelist
Author-email: rusticalex@yahoo.com
Maintainer: Pyrustic Evangelist
Maintainer-email: rusticalex@yahoo.com
License: MIT
Keywords: scripting,language,script,project-manager,manager,packaging,release,build,project-init,lightweight,pyrustic,tool,CLI,setup,versioning,git,language-agnostic,productivity
Platform: UNKNOWN
Classifier: Programming Language :: Python :: 3
Classifier: License :: OSI Approved :: MIT License
Classifier: Operating System :: OS Independent
Requires-Python: >=3.5
License-File: LICENSE
